LICENSE
README.md
setup.py
bin/eva
eva4_shell/__init__.py
eva4_shell/ap.py
eva4_shell/charts.py
eva4_shell/cli.py
eva4_shell/client.py
eva4_shell/compl.py
eva4_shell/sharedobj.py
eva4_shell/shell.py
eva4_shell/tools.py
eva_shell.egg-info/PKG-INFO
eva_shell.egg-info/SOURCES.txt
eva_shell.egg-info/dependency_links.txt
eva_shell.egg-info/requires.txt
eva_shell.egg-info/top_level.txt