Metadata-Version: 2.4
Name: eva-shell
Version: 0.2.44
Summary: EVA ICS v4 shell
Home-page: https://github.com/eva-ics/eva4
Author: Bohemia Automation / Altertech
Author-email: div@altertech.com
License: Apache License 2.0
Classifier: Programming Language :: Python :: 3
Classifier: License :: OSI Approved :: MIT License
Classifier: Topic :: Communications
License-File: LICENSE
Requires-Dist: busrt>=0.1.0
Requires-Dist: evaics>=0.0.32
Requires-Dist: yedb[cli]>=0.2.25
Requires-Dist: argcomplete>=2.0.0
Requires-Dist: python-dateutil>=2.7.3
Requires-Dist: neotermcolor>=2.0.10
Requires-Dist: pyyaml>=6.0
Requires-Dist: pygments>=2.11.2
Requires-Dist: pytz>=2024.1
Requires-Dist: pwinput>=1.0.2
Requires-Dist: tzlocal>=5.1
Dynamic: author
Dynamic: author-email
Dynamic: classifier
Dynamic: description
Dynamic: description-content-type
Dynamic: home-page
Dynamic: license
Dynamic: license-file
Dynamic: requires-dist
Dynamic: summary
